task_manager/__init__.py
task_manager/__version__.py
task_manager/task_manager.py
tests/__init__.py
tests/test_task_manager.py
python_task_manager-0.1.0.dist-info/LICENSE
python_task_manager-0.1.0.dist-info/METADATA
python_task_manager-0.1.0.dist-info/WHEEL
python_task_manager-0.1.0.dist-info/top_level.txt
python_task_manager-0.1.0.dist-info/RECORD
