Metadata-Version: 2.1
Name: python-task-manager
Version: 0.1.0
Summary: python-task-manager - Simple Task Manager for subsequent running of python functions
Home-page: https://github.com/phasi/python-task-manager
Author: Pasi Talvitie
Author-email: pasi@antispam.com
License: GNU/GPL 3.0
Keywords: task manager
Classifier: Development Status :: 4 - Beta
Classifier: Intended Audience :: Developers
Classifier: Programming Language :: Python :: 3.7
Requires-Python: >=3.7
License-File: LICENSE
